{
  "_class": "group",
  "do_objectID": "30065DF8-362F-49E2-B269-0B7A327FC530",
  "exportOptions": {
    "_class": "exportOptions",
    "exportFormats": [
    ],
    "includedLayerIds": [
    ],
    "layerOptions": 0,
    "shouldTrim": false
  },
  "frame": {
    "_class": "rect",
    "constrainProportions": false,
    "height": 46,
    "width": 361,
    "x": 0,
    "y": 87
  },
  "hasClickThrough": false,
  "isFlippedHorizontal": false,
  "isFlippedVertical": false,
  "isLocked": false,
  "isVisible": false,
  "layerListExpandedType": 0,
  "layers": [
    {
      "class": "shapeGroup",
      "id": "335FED71-5E21-4307-B294-6EF2A768A10B"
    },
    {
      "class": "shapeGroup",
      "id": "A69785C5-2C83-448D-AF68-1D78ACC9DE8A"
    },
    {
      "class": "text",
      "id": "D3325250-D9B5-4477-A951-6F9505E1D1D5"
    },
    {
      "class": "text",
      "id": "7CA4B9F9-7425-4D7C-9A67-9459CC83D11A"
    }
  ],
  "name": "Group 4",
  "nameIsFixed": false,
  "resizingConstraint": 63,
  "resizingType": 0,
  "rotation": 0,
  "shouldBreakMaskChain": false,
  "style": {
    "_class": "style",
    "endDecorationType": 0,
    "miterLimit": 10,
    "startDecorationType": 0
  }
}