{
  "_class": "shapeGroup",
  "clippingMaskMode": 0,
  "do_objectID": "CD6B49AA-5841-4B23-AEA6-431C257432A1",
  "exportOptions": {
    "_class": "exportOptions",
    "do_objectID": "4C57533F-1EF5-4F16-A42C-0ADA7F5DD94A",
    "exportFormats": [
    ],
    "includedLayerIds": [
    ],
    "layerOptions": 0,
    "shouldTrim": false
  },
  "frame": {
    "_class": "rect",
    "constrainProportions": false,
    "do_objectID": "D1FB67A8-E0F4-437D-8B7D-E5A7C78178AC",
    "height": 7.624217004139712,
    "width": 23.89174241337741,
    "x": 0,
    "y": 5.919591613105176
  },
  "hasClickThrough": false,
  "hasClippingMask": false,
  "isFlippedHorizontal": false,
  "isFlippedVertical": false,
  "isLocked": false,
  "isVisible": true,
  "layerListExpandedType": 0,
  "layers": [
    {
      "class": "shapePath",
      "id": "676B97F3-3425-4791-A8E0-32A1DFE389BB"
    },
    {
      "class": "shapePath",
      "id": "5F326CAB-898F-45C2-8963-4CB3479D248A"
    }
  ],
  "name": "Path 116 Copy",
  "nameIsFixed": false,
  "resizingConstraint": 63,
  "resizingType": 0,
  "rotation": 0,
  "shouldBreakMaskChain": false,
  "style": {
    "_class": "style",
    "blur": {
      "_class": "blur",
      "center": "{0.5, 0.5}",
      "do_objectID": "9041A495-C883-4E89-BFD8-DB84E1979DEC",
      "isEnabled": false,
      "motionAngle": 0,
      "radius": 3,
      "type": 0
    },
    "borderOptions": {
      "_class": "borderOptions",
      "dashPattern": [
      ],
      "do_objectID": "EA370403-CCB6-49E0-B5E9-890A427348D7",
      "isEnabled": false,
      "lineCapStyle": 1,
      "lineJoinStyle": 1
    },
    "borders": [
      {
        "_class": "border",
        "color": {
          "_class": "color",
          "alpha": 1,
          "blue": 0.2901960784313726,
          "green": 0.2901960784313726,
          "red": 0.2901960784313726
        },
        "fillType": 0,
        "isEnabled": true,
        "position": 0,
        "thickness": 0.8999999999999999
      }
    ],
    "do_objectID": "4F95CB53-3674-4C6B-8B6B-D9EE5F88D983",
    "endDecorationType": 0,
    "fills": [
      {
        "_class": "fill",
        "color": {
          "_class": "color",
          "alpha": 1,
          "blue": 0.847,
          "green": 0.847,
          "red": 0.847
        },
        "fillType": 0,
        "isEnabled": false,
        "noiseIndex": 0,
        "noiseIntensity": 0,
        "patternFillType": 1,
        "patternTileScale": 1
      }
    ],
    "miterLimit": 10,
    "startDecorationType": 0
  },
  "windingRule": 1
}