{
  "_class": "group",
  "do_objectID": "FA79BFDF-C6FC-41FD-A0E7-0A94A66E8B8D",
  "exportOptions": {
    "_class": "exportOptions",
    "do_objectID": "7FBA9F7D-3E8D-4A7B-83AA-72C1524AE68A",
    "exportFormats": [
      {
        "_class": "exportFormat",
        "absoluteSize": 0,
        "fileFormat": "png",
        "name": "",
        "namingScheme": 0,
        "scale": 2,
        "visibleScaleType": 0
      }
    ],
    "includedLayerIds": [
    ],
    "layerOptions": 0,
    "shouldTrim": false
  },
  "frame": {
    "_class": "rect",
    "constrainProportions": false,
    "do_objectID": "4BF40CC3-0CB0-4302-ABF7-75D5E8314BD9",
    "height": 55,
    "width": 360,
    "x": 0,
    "y": 0
  },
  "hasClickThrough": false,
  "isFlippedHorizontal": false,
  "isFlippedVertical": false,
  "isLocked": false,
  "isVisible": true,
  "layerListExpandedType": 2,
  "layers": [
    {
      "class": "shapeGroup",
      "id": "874C2BFD-1E10-443E-830D-A8563E2D6858"
    },
    {
      "class": "text",
      "id": "21ED0FA8-C483-49FA-BBCD-F6BE01BCC93F"
    },
    {
      "class": "text",
      "id": "5C3DE2C0-84DD-4CDF-9363-E137162A8EB0"
    }
  ],
  "name": "Group Copy",
  "nameIsFixed": false,
  "resizingConstraint": 63,
  "resizingType": 0,
  "rotation": 0,
  "shouldBreakMaskChain": false,
  "style": {
    "_class": "style",
    "do_objectID": "50B11A2E-53F9-4172-BE31-30E59D768610",
    "endDecorationType": 0,
    "miterLimit": 10,
    "startDecorationType": 0
  }
}