{
  "_class": "artboard",
  "backgroundColor": {
    "_class": "color",
    "alpha": 1,
    "blue": 0.9568627450980391,
    "green": 0.9529411764705882,
    "red": 0.9490196078431372
  },
  "do_objectID": "85DFF46E-5A82-40FA-A05D-C10EA6C0DB49",
  "exportOptions": {
    "_class": "exportOptions",
    "exportFormats": [
      {
        "_class": "exportFormat",
        "absoluteSize": 0,
        "fileFormat": "png",
        "name": "",
        "namingScheme": 0,
        "scale": 2,
        "visibleScaleType": 0
      }
    ],
    "includedLayerIds": [
    ],
    "layerOptions": 0,
    "shouldTrim": false
  },
  "frame": {
    "_class": "rect",
    "constrainProportions": false,
    "height": 3216,
    "width": 1920,
    "x": 7220,
    "y": -6711
  },
  "hasBackgroundColor": true,
  "hasClickThrough": true,
  "horizontalRulerData": {
    "_class": "rulerData",
    "base": 0,
    "guides": [
    ]
  },
  "includeBackgroundColorInExport": true,
  "includeInCloudUpload": true,
  "isFlippedHorizontal": false,
  "isFlippedVertical": false,
  "isFlowHome": false,
  "isLocked": false,
  "isVisible": true,
  "layerListExpandedType": 2,
  "layers": [
    {
      "class": "shapeGroup",
      "id": "FB82693B-4369-49BF-9B83-43A1E08CF66C"
    },
    {
      "class": "symbolInstance",
      "id": "5AE187A3-7ACB-4153-BE36-FADD51D210A1"
    },
    {
      "class": "text",
      "id": "5ACED32F-B33E-49E8-BA9B-8DCD9977E393"
    },
    {
      "class": "group",
      "id": "1886FC06-9E4D-4E5E-BEB2-342C0AC24969"
    },
    {
      "class": "group",
      "id": "FA677E44-A0FB-4F5A-B0B7-36D8E2568CC7"
    },
    {
      "class": "group",
      "id": "FFE00CA3-8B10-4483-8736-4BA42A62CDD5"
    },
    {
      "class": "text",
      "id": "7FDE384D-0AC7-44CE-AAA4-1118520FE107"
    },
    {
      "class": "group",
      "id": "BE9D61E4-80FF-42E6-9991-2E1D50EB62AF"
    },
    {
      "class": "group",
      "id": "B221E189-C976-49C9-81F4-1206978C74DD"
    },
    {
      "class": "group",
      "id": "BDD6202A-4815-4007-A653-DE37EB5F81E9"
    },
    {
      "class": "group",
      "id": "575C535C-784A-46F4-A3BA-7F8388E04FBB"
    },
    {
      "class": "symbolInstance",
      "id": "973B9AC5-C9B7-4DF5-BB31-5E710F905101"
    },
    {
      "class": "shapeGroup",
      "id": "68816E1E-E6FB-4886-B22A-D44B0FE11E0E"
    },
    {
      "class": "shapeGroup",
      "id": "23220ADA-14CB-4531-918D-40B65574BEBD"
    },
    {
      "class": "shapeGroup",
      "id": "2D9165FD-4C83-427B-9FB6-04E0761732E0"
    },
    {
      "class": "group",
      "id": "154BC258-06CC-45D0-8643-33D715415472"
    },
    {
      "class": "group",
      "id": "E8406D6D-B1B7-44DD-AE30-03DD2B291151"
    },
    {
      "class": "group",
      "id": "16027889-BA39-44CC-AE77-B41CB9FB3966"
    },
    {
      "class": "group",
      "id": "A299BDCE-3243-4730-B320-73CEE7B409A1"
    },
    {
      "class": "group",
      "id": "6ABDEC37-BE5D-4326-BB9A-09F15A729FA1"
    },
    {
      "class": "group",
      "id": "89227B92-1EE3-49CE-9F2D-E0D6DE68E359"
    },
    {
      "class": "shapeGroup",
      "id": "B3E11CB2-7DB2-4F8A-B382-2F6BF0B5C9BB"
    },
    {
      "class": "shapeGroup",
      "id": "6A101A84-5D2A-4E54-A6A8-358B7AAA76DD"
    },
    {
      "class": "group",
      "id": "ED5DA683-234E-455F-BEF9-F809611AFB65"
    },
    {
      "class": "text",
      "id": "144B943A-A650-4F6E-B240-CC7E86643F86"
    },
    {
      "class": "shapeGroup",
      "id": "6008DF7A-069B-49B7-BC4F-E36AA1061B55"
    },
    {
      "class": "group",
      "id": "ABA73541-07BF-49A1-A009-86C042B0DB76"
    },
    {
      "class": "shapeGroup",
      "id": "26A014F1-7EDF-4D72-A42A-8C3C5080BE1F"
    },
    {
      "class": "symbolInstance",
      "id": "7D92FD9A-4FC3-4951-B3E3-E8B283B9571B"
    },
    {
      "class": "symbolInstance",
      "id": "D5A46E14-C858-40AF-8711-6D8B8988B1CD"
    },
    {
      "class": "shapeGroup",
      "id": "222F19E2-E764-40D3-AF24-0E2108A40DC2"
    },
    {
      "class": "shapeGroup",
      "id": "C14EB12C-76FF-44E1-B58A-B654DBE3FB79"
    },
    {
      "class": "shapeGroup",
      "id": "DA46643E-D242-4772-8286-124D90AB884E"
    }
  ],
  "name": "Campaign Detail - Zakat",
  "nameIsFixed": true,
  "presetDictionary": {
    "allowResizedMatching": 0,
    "height": 1024,
    "name": "Desktop",
    "offersLandscapeVariant": 0,
    "width": 1024
  },
  "resizesContent": false,
  "resizingConstraint": 63,
  "resizingType": 0,
  "rotation": 0,
  "shouldBreakMaskChain": true,
  "style": {
    "_class": "style",
    "endDecorationType": 0,
    "miterLimit": 10,
    "startDecorationType": 0
  },
  "verticalRulerData": {
    "_class": "rulerData",
    "base": 0,
    "guides": [
    ]
  }
}