{
  "_class": "shapePath",
  "booleanOperation": -1,
  "do_objectID": "BFAD105D-02E5-4E7B-8B23-E44123AF061D",
  "edited": true,
  "exportOptions": {
    "_class": "exportOptions",
    "do_objectID": "B7F2D2F5-D8FF-4BED-A246-2F3D3DF95D9E",
    "exportFormats": [
    ],
    "includedLayerIds": [
    ],
    "layerOptions": 0,
    "shouldTrim": false
  },
  "frame": {
    "_class": "rect",
    "constrainProportions": false,
    "do_objectID": "6058CF60-0C4A-47EE-88DB-B9F158F5925F",
    "height": 2,
    "width": 328,
    "x": 0,
    "y": 0
  },
  "isClosed": false,
  "isFlippedHorizontal": false,
  "isFlippedVertical": false,
  "isLocked": false,
  "isVisible": true,
  "layerListExpandedType": 0,
  "name": "Path",
  "nameIsFixed": false,
  "pointRadiusBehaviour": 1,
  "points": [
    {
      "_class": "curvePoint",
      "cornerRadius": 0,
      "curveFrom": "{0, 0.5}",
      "curveMode": 1,
      "curveTo": "{0, 0.5}",
      "hasCurveFrom": false,
      "hasCurveTo": false,
      "point": "{0, 0.5}"
    },
    {
      "_class": "curvePoint",
      "cornerRadius": 0,
      "curveFrom": "{0.82317073170731614, 0.5}",
      "curveMode": 1,
      "curveTo": "{0.82317073170731614, 0.5}",
      "hasCurveFrom": false,
      "hasCurveTo": false,
      "point": "{1, 0.5}"
    }
  ],
  "resizingConstraint": 63,
  "resizingType": 0,
  "rotation": 0,
  "shouldBreakMaskChain": false
}