{
  "_class": "group",
  "do_objectID": "6C312474-9652-42EB-9BE7-9895C70CC8C9",
  "exportOptions": {
    "_class": "exportOptions",
    "exportFormats": [
    ],
    "includedLayerIds": [
    ],
    "layerOptions": 0,
    "shouldTrim": false
  },
  "frame": {
    "_class": "rect",
    "constrainProportions": false,
    "height": 30,
    "width": 120,
    "x": 220,
    "y": 15
  },
  "hasClickThrough": false,
  "isFlippedHorizontal": false,
  "isFlippedVertical": false,
  "isLocked": false,
  "isVisible": true,
  "layerListExpandedType": 0,
  "layers": [
    {
      "class": "shapeGroup",
      "id": "3CCE9B92-0C4A-47CD-943D-CCBB8E52FCDD"
    },
    {
      "class": "text",
      "id": "CECDA1CE-1ACB-461E-80E6-42A42C1C512F"
    },
    {
      "class": "text",
      "id": "A0680140-BF3F-44AD-B70E-C4B741F17D3D"
    }
  ],
  "name": "sort-by",
  "nameIsFixed": true,
  "resizingConstraint": 63,
  "resizingType": 0,
  "rotation": 0,
  "shouldBreakMaskChain": false,
  "style": {
    "_class": "style",
    "endDecorationType": 0,
    "miterLimit": 10,
    "startDecorationType": 0
  }
}