{
  "_class": "group",
  "booleanOperation": 0,
  "clippingMaskMode": 0,
  "do_objectID": "2AFDC379-B457-478D-ABF4-C8EE64A9442B",
  "exportOptions": {
    "_class": "exportOptions",
    "do_objectID": "16201541-BEBF-4C0E-913F-4D2E2B57ECC5",
    "exportFormats": [
    ],
    "includedLayerIds": [
    ],
    "layerOptions": 0,
    "shouldTrim": false
  },
  "frame": {
    "_class": "rect",
    "constrainProportions": false,
    "do_objectID": "83E7000C-6E83-431B-9E7A-8958C8A89324",
    "height": 128,
    "width": 360,
    "x": 0,
    "y": 611
  },
  "hasClickThrough": false,
  "hasClippingMask": false,
  "isFixedToViewport": false,
  "isFlippedHorizontal": false,
  "isFlippedVertical": false,
  "isLocked": false,
  "isVisible": true,
  "layerListExpandedType": 2,
  "layers": [
    {
      "class": "text",
      "id": "4FD60E8B-5274-4D8D-B2B5-F2289CC50A21"
    },
    {
      "class": "text",
      "id": "47973DFD-9A0F-460E-A11C-D1E181F5AFD3"
    },
    {
      "class": "group",
      "id": "C532469E-6036-4746-A51F-064265B5E617"
    },
    {
      "class": "symbolInstance",
      "id": "54EF4619-AEE9-4B0D-83ED-353D7DD6F7CA"
    },
    {
      "class": "text",
      "id": "4AD9FBE3-055A-459A-9E9D-F47DE9E5E665"
    },
    {
      "class": "text",
      "id": "A7EE3398-A9AE-47C8-A048-FCCFC6FE5DA2"
    },
    {
      "class": "group",
      "id": "7D579233-FD7D-41AC-BD15-1987063B5D45"
    },
    {
      "class": "rectangle",
      "id": "04E4A55F-C5AA-4DE2-9D07-7EE992E099E7"
    },
    {
      "class": "rectangle",
      "id": "EC246D8A-ABF4-41C7-B88F-B8FCA238049C"
    },
    {
      "class": "rectangle",
      "id": "4333677E-69CF-4C7D-A963-C2F398C07CA7"
    },
    {
      "class": "text",
      "id": "B9D60ED5-9D91-4BE9-B31F-D26E38BC6C5D"
    },
    {
      "class": "text",
      "id": "9823C0CB-0357-4325-B174-75D4B179213C"
    },
    {
      "class": "oval",
      "id": "F8E8D89B-2C7B-4078-9362-341A7B85F65E"
    }
  ],
  "name": "Campaigner",
  "nameIsFixed": true,
  "resizingConstraint": 63,
  "resizingType": 0,
  "rotation": 0,
  "shouldBreakMaskChain": false,
  "style": {
    "_class": "style",
    "do_objectID": "46CFA29D-F905-4192-8737-91FA535644FE",
    "endMarkerType": 0,
    "miterLimit": 10,
    "startMarkerType": 0,
    "windingRule": 1
  }
}