{
  "_class": "shapeGroup",
  "clippingMaskMode": 0,
  "do_objectID": "246DBBBE-A961-4E10-9398-372FD96E1F9A",
  "exportOptions": {
    "_class": "exportOptions",
    "do_objectID": "D132404C-E8C1-4C72-876C-E63DB8971B03",
    "exportFormats": [
    ],
    "includedLayerIds": [
    ],
    "layerOptions": 0,
    "shouldTrim": false
  },
  "frame": {
    "_class": "rect",
    "constrainProportions": false,
    "do_objectID": "E9BDBD07-B0D2-4E98-AC29-E887077366EB",
    "height": 1.47641831852358,
    "width": 1.821862348178137,
    "x": 2.732793522267206,
    "y": 9.596719070403275
  },
  "hasClickThrough": false,
  "hasClippingMask": false,
  "isFlippedHorizontal": false,
  "isFlippedVertical": false,
  "isLocked": false,
  "isVisible": true,
  "layerListExpandedType": 0,
  "layers": [
    {
      "class": "shapePath",
      "id": "4A93778A-3801-48D7-B515-B58125CD0C32"
    }
  ],
  "name": "Rectangle 3",
  "nameIsFixed": false,
  "resizingConstraint": 63,
  "resizingType": 0,
  "rotation": 0,
  "shouldBreakMaskChain": false,
  "style": {
    "_class": "style",
    "blur": {
      "_class": "blur",
      "center": "{0.5, 0.5}",
      "do_objectID": "936AC29E-0721-4C56-968C-AA864599EDC7",
      "isEnabled": false,
      "motionAngle": 0,
      "radius": 2.4,
      "type": 0
    },
    "borderOptions": {
      "_class": "borderOptions",
      "dashPattern": [
      ],
      "do_objectID": "1375189E-463E-41C2-BCBE-028502B9998C",
      "isEnabled": false,
      "lineCapStyle": 1,
      "lineJoinStyle": 0
    },
    "borders": [
      {
        "_class": "border",
        "color": {
          "_class": "color",
          "alpha": 1,
          "blue": 0.2901960784313726,
          "green": 0.2901960784313726,
          "red": 0.2901960784313726
        },
        "fillType": 0,
        "isEnabled": true,
        "position": 0,
        "thickness": 0.72
      }
    ],
    "do_objectID": "43AF7DB1-83DD-44F0-962C-27B8E540D3A4",
    "endDecorationType": 0,
    "fills": [
      {
        "_class": "fill",
        "color": {
          "_class": "color",
          "alpha": 1,
          "blue": 0.847,
          "green": 0.847,
          "red": 0.847
        },
        "fillType": 0,
        "isEnabled": false,
        "noiseIndex": 0,
        "noiseIntensity": 0,
        "patternFillType": 1,
        "patternTileScale": 1
      }
    ],
    "miterLimit": 10,
    "startDecorationType": 0
  },
  "windingRule": 1
}