{
  "_class": "rectangle",
  "booleanOperation": 0,
  "do_objectID": "6A073988-BF86-4DEC-9F44-7E55C5A73835",
  "edited": false,
  "exportOptions": {
    "_class": "exportOptions",
    "do_objectID": "EA5AB5EE-5711-4005-9924-00BCE3133ED5",
    "exportFormats": [
    ],
    "includedLayerIds": [
    ],
    "layerOptions": 0,
    "shouldTrim": false
  },
  "fixedRadius": 0.75,
  "frame": {
    "_class": "rect",
    "constrainProportions": false,
    "do_objectID": "EA88A51F-3707-41C1-8BE6-31A45F52F694",
    "height": 7.620689655172415,
    "width": 1.475409836065573,
    "x": 1.628349891161057,
    "y": 4.562491662846544
  },
  "hasConvertedToNewRoundCorners": true,
  "isClosed": true,
  "isFlippedHorizontal": false,
  "isFlippedVertical": false,
  "isLocked": false,
  "isVisible": true,
  "layerListExpandedType": 0,
  "name": "Rectangle 42",
  "nameIsFixed": false,
  "pointRadiusBehaviour": 1,
  "points": [
    {
      "_class": "curvePoint",
      "cornerRadius": 0.75,
      "curveFrom": "{0, 0}",
      "curveMode": 1,
      "curveTo": "{0, 0}",
      "hasCurveFrom": false,
      "hasCurveTo": false,
      "point": "{0, 0}"
    },
    {
      "_class": "curvePoint",
      "cornerRadius": 0.75,
      "curveFrom": "{1, 0}",
      "curveMode": 1,
      "curveTo": "{1, 0}",
      "hasCurveFrom": false,
      "hasCurveTo": false,
      "point": "{1, 0}"
    },
    {
      "_class": "curvePoint",
      "cornerRadius": 0.75,
      "curveFrom": "{1, 1}",
      "curveMode": 1,
      "curveTo": "{1, 1}",
      "hasCurveFrom": false,
      "hasCurveTo": false,
      "point": "{1, 1}"
    },
    {
      "_class": "curvePoint",
      "cornerRadius": 0.75,
      "curveFrom": "{0, 1}",
      "curveMode": 1,
      "curveTo": "{0, 1}",
      "hasCurveFrom": false,
      "hasCurveTo": false,
      "point": "{0, 1}"
    }
  ],
  "resizingConstraint": 63,
  "resizingType": 0,
  "rotation": -32,
  "shouldBreakMaskChain": false
}