{
  "_class": "shapeGroup",
  "clippingMaskMode": 0,
  "do_objectID": "6A71A5C2-2F47-4F91-8523-36333594527C",
  "exportOptions": {
    "_class": "exportOptions",
    "do_objectID": "3CD60E2A-B621-4603-B29B-8214C6528031",
    "exportFormats": [
    ],
    "includedLayerIds": [
    ],
    "layerOptions": 0,
    "shouldTrim": false
  },
  "frame": {
    "_class": "rect",
    "constrainProportions": false,
    "do_objectID": "C7FB8980-D069-4886-AD98-0D5F2C0C4776",
    "height": 7.335251536731882,
    "width": 7.076923076923078,
    "x": 10.73076923076928,
    "y": 16.66474846326673
  },
  "hasClickThrough": false,
  "hasClippingMask": false,
  "isFlippedHorizontal": false,
  "isFlippedVertical": false,
  "isLocked": false,
  "isVisible": true,
  "layerListExpandedType": 0,
  "layers": [
    {
      "class": "shapePath",
      "id": "AE00238E-10F4-4171-84CE-F595ED03411A"
    }
  ],
  "name": "Rectangle 35",
  "nameIsFixed": false,
  "resizingConstraint": 63,
  "resizingType": 0,
  "rotation": 0,
  "shouldBreakMaskChain": false,
  "style": {
    "_class": "style",
    "blur": {
      "_class": "blur",
      "center": "{0.5, 0.5}",
      "do_objectID": "0534E8B7-C7ED-4DA6-B877-A0487A9D1C65",
      "isEnabled": false,
      "motionAngle": 0,
      "radius": 3,
      "type": 0
    },
    "borders": [
      {
        "_class": "border",
        "color": {
          "_class": "color",
          "alpha": 1,
          "blue": 0.2901960784313726,
          "green": 0.2901960784313726,
          "red": 0.2901960784313726
        },
        "fillType": 0,
        "isEnabled": true,
        "position": 0,
        "thickness": 0.8999999999999999
      }
    ],
    "do_objectID": "316A800B-E822-42F5-A34B-79E844087579",
    "endDecorationType": 0,
    "fills": [
      {
        "_class": "fill",
        "color": {
          "_class": "color",
          "alpha": 1,
          "blue": 0.847,
          "green": 0.847,
          "red": 0.847
        },
        "fillType": 0,
        "isEnabled": false,
        "noiseIndex": 0,
        "noiseIntensity": 0,
        "patternFillType": 1,
        "patternTileScale": 1
      }
    ],
    "miterLimit": 10,
    "startDecorationType": 0
  },
  "windingRule": 1
}