{
  "_class": "shapePath",
  "booleanOperation": -1,
  "do_objectID": "3E3040FF-4981-4A9E-BF0E-4237A7CF9B49",
  "edited": true,
  "exportOptions": {
    "_class": "exportOptions",
    "do_objectID": "5DD3A75F-B08E-4166-AA2F-62F00B401FB6",
    "exportFormats": [
    ],
    "includedLayerIds": [
    ],
    "layerOptions": 0,
    "shouldTrim": false
  },
  "frame": {
    "_class": "rect",
    "constrainProportions": false,
    "do_objectID": "CDA614FA-6B42-4D01-91BC-94B5CDBAFE6B",
    "height": 2,
    "width": 260,
    "x": 0,
    "y": 0
  },
  "isClosed": false,
  "isFlippedHorizontal": false,
  "isFlippedVertical": false,
  "isLocked": false,
  "isVisible": true,
  "layerListExpandedType": 0,
  "name": "Path",
  "nameIsFixed": false,
  "pointRadiusBehaviour": 1,
  "points": [
    {
      "_class": "curvePoint",
      "cornerRadius": 0,
      "curveFrom": "{0, 0.5}",
      "curveMode": 1,
      "curveTo": "{0, 0.5}",
      "hasCurveFrom": false,
      "hasCurveTo": false,
      "point": "{0, 0.5}"
    },
    {
      "_class": "curvePoint",
      "cornerRadius": 0,
      "curveFrom": "{1.0384615384615372, 0.5}",
      "curveMode": 1,
      "curveTo": "{1.0384615384615372, 0.5}",
      "hasCurveFrom": false,
      "hasCurveTo": false,
      "point": "{1, 0.5}"
    }
  ],
  "resizingConstraint": 63,
  "resizingType": 0,
  "rotation": 0,
  "shouldBreakMaskChain": false
}