{
  "_class": "group",
  "booleanOperation": 0,
  "clippingMaskMode": 0,
  "do_objectID": "C4696D7C-68BC-4355-BB74-C51BB3E44A30",
  "exportOptions": {
    "_class": "exportOptions",
    "do_objectID": "DD0087DA-EC7F-47DB-80D4-44DFBCFA3488",
    "exportFormats": [
    ],
    "includedLayerIds": [
    ],
    "layerOptions": 0,
    "shouldTrim": false
  },
  "frame": {
    "_class": "rect",
    "constrainProportions": false,
    "do_objectID": "BCDE52FD-6ED6-48C5-8259-1E076DC25FFD",
    "height": 360,
    "width": 360,
    "x": 0,
    "y": -100
  },
  "hasClickThrough": false,
  "hasClippingMask": false,
  "isFixedToViewport": false,
  "isFlippedHorizontal": false,
  "isFlippedVertical": false,
  "isLocked": false,
  "isVisible": true,
  "layerListExpandedType": 0,
  "layers": [
    {
      "class": "rectangle",
      "id": "87C12CC3-D2D2-4FF8-8D5D-E63244F008A1"
    },
    {
      "class": "bitmap",
      "id": "44F1207B-3D8E-41ED-8253-9B1EF9D25536"
    }
  ],
  "name": "masjid",
  "nameIsFixed": false,
  "originalObjectID": "0846EF3C-73E1-4A22-9504-85B751101455",
  "resizingConstraint": 63,
  "resizingType": 0,
  "rotation": 0,
  "shouldBreakMaskChain": false,
  "style": {
    "_class": "style",
    "do_objectID": "625E50AD-7F0F-492C-B964-CC5F837F9413",
    "endMarkerType": 0,
    "miterLimit": 10,
    "startMarkerType": 0,
    "windingRule": 1
  }
}