{
  "_class": "group",
  "booleanOperation": 0,
  "clippingMaskMode": 0,
  "do_objectID": "47C72D14-8B1E-4E26-ACD7-FEBC623ED808",
  "exportOptions": {
    "_class": "exportOptions",
    "do_objectID": "7281F2D8-ACFB-46D1-837A-FCA377E84C7B",
    "exportFormats": [
    ],
    "includedLayerIds": [
    ],
    "layerOptions": 0,
    "shouldTrim": false
  },
  "frame": {
    "_class": "rect",
    "constrainProportions": false,
    "do_objectID": "DE15E2A2-8000-457D-920C-A87F0E889C81",
    "height": 53,
    "width": 321,
    "x": 16,
    "y": 717
  },
  "hasClickThrough": false,
  "hasClippingMask": false,
  "isFixedToViewport": false,
  "isFlippedHorizontal": false,
  "isFlippedVertical": false,
  "isLocked": false,
  "isVisible": true,
  "layerListExpandedType": 0,
  "layers": [
    {
      "class": "text",
      "id": "4BB86C84-B0C5-42E9-88CE-D748D551CD39"
    },
    {
      "class": "text",
      "id": "3D3C8D9A-E58B-4FAB-B84A-F090D6A1C34E"
    },
    {
      "class": "symbolInstance",
      "id": "6531D4E2-D9C9-4EF5-8ADD-7E2C215609BA"
    }
  ],
  "name": "Group 3",
  "nameIsFixed": false,
  "resizingConstraint": 63,
  "resizingType": 0,
  "rotation": 0,
  "shouldBreakMaskChain": false,
  "style": {
    "_class": "style",
    "do_objectID": "45DA46BD-6524-4E3A-9191-BFD320A4B22A",
    "endMarkerType": 0,
    "miterLimit": 10,
    "startMarkerType": 0,
    "windingRule": 1
  }
}