{
  "_class": "shapePath",
  "booleanOperation": -1,
  "do_objectID": "8606CB81-430F-40DC-90FF-C30C0C6D9D55",
  "edited": true,
  "exportOptions": {
    "_class": "exportOptions",
    "do_objectID": "5EC8A5D0-3F77-4ABE-824B-09E77574F3BE",
    "exportFormats": [
    ],
    "includedLayerIds": [
    ],
    "layerOptions": 0,
    "shouldTrim": false
  },
  "frame": {
    "_class": "rect",
    "constrainProportions": false,
    "do_objectID": "4FAF0A50-C3DD-4FA4-B4B7-5D5BF4626704",
    "height": 0.8999999999999999,
    "width": 2.434782608695652,
    "x": 0,
    "y": 0
  },
  "isClosed": false,
  "isFlippedHorizontal": false,
  "isFlippedVertical": false,
  "isLocked": false,
  "isVisible": true,
  "layerListExpandedType": 0,
  "name": "Path",
  "nameIsFixed": false,
  "pointRadiusBehaviour": 1,
  "points": [
    {
      "_class": "curvePoint",
      "cornerRadius": 0,
      "curveFrom": "{0.12500000000000003, 0.66666666666666663}",
      "curveMode": 1,
      "curveTo": "{0.12500000000000003, 0.66666666666666663}",
      "hasCurveFrom": false,
      "hasCurveTo": false,
      "point": "{0.062500000000000014, 0.5}"
    },
    {
      "_class": "curvePoint",
      "cornerRadius": 0,
      "curveFrom": "{0.25000000000000006, 1}",
      "curveMode": 1,
      "curveTo": "{0.25000000000000006, 1}",
      "hasCurveFrom": false,
      "hasCurveTo": false,
      "point": "{0.9375, 0.5}"
    }
  ],
  "resizingConstraint": 63,
  "resizingType": 0,
  "rotation": 0,
  "shouldBreakMaskChain": false
}